[
  {
    "id": "node_0",
    "status": "idle",
    "last_ping": "2025-06-29T23:34:06.517586"
  },
  {
    "id": "node_1",
    "status": "idle",
    "last_ping": "2025-06-29T23:34:06.517596"
  },
  {
    "id": "node_2",
    "status": "idle",
    "last_ping": "2025-06-29T23:34:06.517600"
  },
  {
    "id": "node_3",
    "status": "idle",
    "last_ping": "2025-06-29T23:34:06.517603"
  },
  {
    "id": "node_4",
    "status": "idle",
    "last_ping": "2025-06-29T23:34:06.517606"
  },
  {
    "id": "node_5",
    "status": "processing",
    "last_ping": "2025-06-29T23:34:06.517609"
  },
  {
    "id": "node_6",
    "status": "idle",
    "last_ping": "2025-06-29T23:34:06.517611"
  },
  {
    "id": "node_7",
    "status": "processing",
    "last_ping": "2025-06-29T23:34:06.517617"
  },
  {
    "id": "node_8",
    "status": "online",
    "last_ping": "2025-06-29T23:34:06.517620"
  },
  {
    "id": "node_9",
    "status": "idle",
    "last_ping": "2025-06-29T23:34:06.517623"
  }
]